nlpipes/__init__.py
nlpipes/auto_pipeline.py
nlpipes/callbacks/__init__.py
nlpipes/callbacks/callbacks.py
nlpipes/configurations/bert_config.py
nlpipes/configurations/card_config.py
nlpipes/data/__init__.py
nlpipes/data/data_augmentors.py
nlpipes/data/data_cleaners.py
nlpipes/data/data_converters.py
nlpipes/data/data_loaders.py
nlpipes/data/data_processors.py
nlpipes/data/data_selectors.py
nlpipes/data/data_splitters.py
nlpipes/data/data_types.py
nlpipes/data/data_utils.py
nlpipes/layers/bert_layers.py
nlpipes/losses/losses.py
nlpipes/metrics/__init__.py
nlpipes/metrics/confusion.py
nlpipes/metrics/diversity.py
nlpipes/metrics/similarity.py
nlpipes/models/classification_models.py
nlpipes/models/language_models.py
nlpipes/optimization/optimizers.py
nlpipes/optimization/schedulers.py
nlpipes/pipelines/__init__.py
nlpipes/pipelines/base_pipeline.py
nlpipes/pipelines/class_label_classification_pipelines.py
nlpipes/pipelines/language_modeling_pipelines.py
nlpipes/pipelines/mono_label_classification_pipelines.py
nlpipes/pipelines/multi_label_classification_pipelines.py
nlpipes/trainers/__init__.py
nlpipes/trainers/trainers.py
nlpipes-0.1.18.dist-info/METADATA
nlpipes-0.1.18.dist-info/WHEEL
nlpipes-0.1.18.dist-info/RECORD
