Metadata-Version: 2.1
Name: nlpipes
Version: 0.1.18
Summary: Text Classification with Transformers
License: Apache 2.0
Author: Ayhan UYANIK
Author-email: ayhan.uyanik@renault.com
Requires-Python: >=3.7,<4.0
Classifier: License :: Other/Proprietary License
Classifier: Programming Language :: Python :: 3
Classifier: Programming Language :: Python :: 3.7
Classifier: Programming Language :: Python :: 3.8
Classifier: Programming Language :: Python :: 3.9
Classifier: Programming Language :: Python :: 3.10
Classifier: Programming Language :: Python :: 3.11
Requires-Dist: ftfy (>=6.1.1,<7.0.0)
Requires-Dist: numpy (>=1.21.0,<2.0.0)
Requires-Dist: pandas (>=1.3.5,<2.0.0)
Requires-Dist: scipy (>=1.7.3,<2.0.0)
Requires-Dist: tensorflow (>=2.11.0,<3.0.0)
Requires-Dist: tokenizers (>=0.13.0,<0.14.0)
Requires-Dist: tqdm (>=4.64.0,<5.0.0)
Requires-Dist: transformers (>=4.24.0,<5.0.0)
